midonet/__init__.py
midonet/flake8_import_order/__init__.py
midonet/flake8_import_order/styles.py
midonet/locale/en_GB/LC_MESSAGES/midonet.po
midonet/neutron/__init__.py
midonet/neutron/_i18n.py
midonet/neutron/agent/__init__.py
midonet/neutron/agent/interface.py
midonet/neutron/agent/midonet_driver.py
midonet/neutron/client/__init__.py
midonet/neutron/client/api.py
midonet/neutron/client/base.py
midonet/neutron/client/cluster.py
midonet/neutron/common/__init__.py
midonet/neutron/common/config.py
midonet/neutron/common/constants.py
midonet/neutron/common/exceptions.py
midonet/neutron/common/utils.py
midonet/neutron/db/__init__.py
midonet/neutron/db/bgp_db_midonet.py
midonet/neutron/db/bgp_speaker_router_insertion_db.py
midonet/neutron/db/bgp_speaker_router_insertion_model.py
midonet/neutron/db/data_state_db.py
midonet/neutron/db/data_version_db.py
midonet/neutron/db/gateway_device.py
midonet/neutron/db/l2gateway_midonet.py
midonet/neutron/db/l3_db_midonet.py
midonet/neutron/db/port_binding_db.py
midonet/neutron/db/provider_network_db.py
midonet/neutron/db/task_db.py
midonet/neutron/db/migration/__init__.py
midonet/neutron/db/migration/alembic.ini
midonet/neutron/db/migration/cli.py
midonet/neutron/db/migration/alembic_migration/README
midonet/neutron/db/migration/alembic_migration/__init__.py
midonet/neutron/db/migration/alembic_migration/env.py
midonet/neutron/db/migration/alembic_migration/script.py.mako
midonet/neutron/db/migration/alembic_migration/versions/19808c5df22a_add_agent_membership.py
midonet/neutron/db/migration/alembic_migration/versions/25aeae45d4ad_add_task.py
midonet/neutron/db/migration/alembic_migration/versions/3fe2bca71c72_add_port_binding.py
midonet/neutron/db/migration/alembic_migration/versions/421564f630b1_add_dynamic_routing.py
midonet/neutron/db/migration/alembic_migration/versions/422da2897701_add_network_binding_table.py
midonet/neutron/db/migration/alembic_migration/versions/CONTRACT_HEAD
networking_midonet-11.0.0.dist-info/DESCRIPTION.rst
networking_midonet-11.0.0.dist-info/METADATA
networking_midonet-11.0.0.dist-info/RECORD
networking_midonet-11.0.0.dist-info/WHEEL
networking_midonet-11.0.0.dist-info/entry_points.txt
networking_midonet-11.0.0.dist-info/metadata.json
networking_midonet-11.0.0.dist-info/pbr.json
networking_midonet-11.0.0.dist-info/top_level.txt
