Metadata-Version: 2.0
Name: networking-midonet
Version: 11.0.0
Summary: OpenStack MidoNet Neutron Plugin
Home-page: https://docs.openstack.org/networking-midonet/latest/
Author: OpenStack
Author-email: openstack-discuss@lists.openstack.org
License: UNKNOWN
Platform: UNKNOWN
Classifier: Environment :: OpenStack
Classifier: Intended Audience :: Information Technology
Classifier: Intended Audience :: System Administrators
Classifier: License :: OSI Approved :: Apache Software License
Classifier: Operating System :: POSIX :: Linux
Classifier: Programming Language :: Python
Classifier: Programming Language :: Python :: 3
Classifier: Programming Language :: Python :: 3.6
Classifier: Programming Language :: Python :: 3.7
Classifier: Programming Language :: Python :: 3 :: Only
Classifier: Programming Language :: Python :: Implementation :: CPython
Requires-Python: >=3.6
Requires-Dist: Babel (!=2.4.0,>=2.3.4)
Requires-Dist: neutron-lib (>=1.18.0)
Requires-Dist: neutron (>=13.0.0.0b1)
Requires-Dist: pbr (!=2.1.0,>=2.0.0)
Requires-Dist: python-neutronclient (>=6.8.0)
